rail_score_sdk/__init__.py
rail_score_sdk/client.py
rail_score_sdk/exceptions.py
rail_score_sdk/models.py
rail_score_sdk-1.0.1.dist-info/licenses/LICENSE
rail_score_sdk-1.0.1.dist-info/METADATA
rail_score_sdk-1.0.1.dist-info/WHEEL
rail_score_sdk-1.0.1.dist-info/top_level.txt
rail_score_sdk-1.0.1.dist-info/RECORD
