Metadata-Version: 2.4
Name: rail-score-sdk
Version: 1.0.1
Summary: Official Python SDK for RAIL Score API - Responsible AI Content Evaluation
Home-page: https://github.com/RAILethicsHub/rail-score/tree/main/python
Author: Responsible AI Labs Team
Author-email: Responsible AI Labs Team <research@responsibleailabs.ai>
Maintainer-email: Responsible AI Labs Team <research@responsibleailabs.ai>
License-Expression: MIT
Project-URL: Homepage, https://github.com/RAILethicsHub/rail-score/tree/main/python
Project-URL: Documentation, https://responsibleailabs.ai/developer/docs
Project-URL: API Reference, https://responsibleailabs.ai/developers/api-ref
Project-URL: Repository, https://github.com/RAILethicsHub/rail-score
Project-URL: Bug Reports, https://github.com/RAILethicsHub/rail-score/issues
Project-URL: Changelog, https://github.com/RAILethicsHub/rail-score/blob/main/python/CHANGELOG.md
Keywords: rail,ai-ethics,content-evaluation,responsible-ai,ai-safety,content-moderation
Classifier: Development Status :: 4 - Beta
Classifier: Intended Audience :: Developers
Classifier: Topic :: Software Development :: Libraries :: Python Modules
Classifier: Topic :: Scientific/Engineering :: Artificial Intelligence
Classifier: Programming Language :: Python :: 3
Classifier: Programming Language :: Python :: 3.8
Classifier: Programming Language :: Python :: 3.9
Classifier: Programming Language :: Python :: 3.10
Classifier: Programming Language :: Python :: 3.11
Classifier: Programming Language :: Python :: 3.12
Classifier: Operating System :: OS Independent
Requires-Python: >=3.8
License-File: LICENSE
Requires-Dist: requests>=2.28.0
Provides-Extra: dev
Requires-Dist: pytest>=7.0.0; extra == "dev"
Requires-Dist: pytest-cov>=4.0.0; extra == "dev"
Requires-Dist: black>=22.0.0; extra == "dev"
Requires-Dist: flake8>=5.0.0; extra == "dev"
Requires-Dist: mypy>=0.990; extra == "dev"
Requires-Dist: types-requests>=2.28.0; extra == "dev"
Dynamic: author
Dynamic: home-page
Dynamic: license-file
Dynamic: requires-python
